{
  "appPageId" : "cf05a5d2-faeb-4a86-888b-5bccd9b17a4d",
  "componentName" : "siteforce:sldsOneColLayout",
  "id" : "de822ac8-9fcf-431f-a64b-0d2417b3a772",
  "label" : "User Settings",
  "regions" : [ {
    "id" : "94ce410d-23d7-43de-ad9d-18cdafef2cc7",
    "regionName" : "header",
    "type" : "region"
  }, {
    "components" : [ {
      "componentAttributes" : {
        "accountSectionTitle" : "Account",
        "accountTabName" : "Account Management",
        "connectedSourcesTabName" : "Connected Sources",
        "deleteAccountButtonTitle" : "Deactivate My Account",
        "deleteAccountConfirmationPopupBody" : "After you deactivate your account, you'll lose access to this site.",
        "deleteAccountConfirmationPopupButtonTitle" : "Got It",
        "deleteAccountConfirmationPopupTitle" : "Deactivate your account?",
        "deleteAccountErrorMessage" : "Something went wrong. Contact your site administrator.",
        "deleteAccountSectionTitle" : "Deactivate Account",
        "emailNotificationsTitle" : "Email Notifications",
        "emailSectionDescText" : "When email notifications are enabled, email me when someone:",
        "hideAccountDeleteSection" : true,
        "hideChatterNotificationSettings" : false,
        "hideConnectedSources" : false,
        "hideEmailNotificationSettings" : false,
        "hideProfileVisibilitySettings" : false,
        "id" : "{!recordId}",
        "locationTitle" : "Location",
        "profileSectionDescText" : "Customize who is able to see what on your profile page",
        "profileSectionToolTipText" : "Restricted: Visible to the employees of the company that created the site. Members: Visible to logged-in members. Public: Visible to anyone viewing pages that don't require login.",
        "profileVisibilityTitle" : "Profile Visibility",
        "settingsPageTitle" : "My Settings"
      },
      "componentName" : "forceCommunity:userSettingsCustomizable",
      "id" : "b600acbb-eaac-48dd-97f5-9d067ecb4bf6",
      "renderPriority" : "NEUTRAL",
      "renditionMap" : { },
      "type" : "component"
    } ],
    "id" : "1811f75e-1121-4f37-a54c-6300e7f5c396",
    "regionName" : "content",
    "type" : "region"
  }, {
    "id" : "6db9e5e0-61a1-43c9-8fc4-659ea7827c81",
    "regionName" : "footer",
    "type" : "region"
  } ],
  "themeLayoutType" : "Inner",
  "type" : "view",
  "viewType" : "usersettings"
}